Workbook

Sheet Dashboard
A1: SEU BETO BURGER • PAINEL DE MÉTRICAS
A2: Dashboard gerencial fictício • vendas, operação, promoções presenciais e fidelização
A3: Período | B3: Todos
A5: Faturamento | B5: =IF($B$3="Todos",SUM(Resumo_Mensal!$F$2:$F$10),SUMIF(Resumo_Mensal!$A$2:$A$10,$B$3,Resumo_Mensal!$F$2:$F$10)) -> 419060.69 | D5: Clientes | E5: =IF($B$3="Todos",SUM(Resumo_Mensal!$B$2:$B$10),SUMIF(Resumo_Mensal!$A$2:$A$10,$B$3,Resumo_Mensal!$B$2:$B$10)) -> 14632 | G5: Ticket Médio | H5: =IFERROR(IF($B$3="Todos",SUM(Resumo_Mensal!$F$2:$F$10)/SUM(Resumo_Mensal!$E$2:$E$10),SUMIF(Resumo_Mensal!$A$2:$A$10,$B$3,Resumo_Mensal!$F$2:$F$10)/SUMIF(Resumo_Mensal!$A$2:$A$10,$B$3,Resumo_Mensal!$E$2:$E$10)),0) -> 29.237472 | J5: Taxa Recompra | K5: =IFERROR(IF($B$3="Todos",SUM(Resumo_Mensal!$D$2:$D$10)/SUM(Resumo_Mensal!$B$2:$B$10),SUMIF(Resumo_Mensal!$A$2:$A$10,$B$3,Resumo_Mensal!$D$2:$D$10)/SUMIF(Resumo_Mensal!$A$2:$A$10,$B$3,Resumo_Mensal!$B$2:$B$10)),0) -> 0.43685074
A8: Lucro Operacional | B8: =IF($B$3="Todos",SUM(Resumo_Mensal!$I$2:$I$10),SUMIF(Resumo_Mensal!$A$2:$A$10,$B$3,Resumo_Mensal!$I$2:$I$10)) -> 175964.92 | D8: Combos Vendidos | E8: =IF($B$3="Todos",SUM(Resumo_Mensal!$L$2:$L$10),SUMIF(Resumo_Mensal!$A$2:$A$10,$B$3,Resumo_Mensal!$L$2:$L$10)) -> 3882 | G8: Cartões Fidelidade | H8: =IF($B$3="Todos",SUM(Resumo_Mensal!$M$2:$M$10),SUMIF(Resumo_Mensal!$A$2:$A$10,$B$3,Resumo_Mensal!$M$2:$M$10)) -> 1418 | J8: Cupons Utilizados | K8: =IF($B$3="Todos",SUM(Resumo_Mensal!$O$2:$O$10),SUMIF(Resumo_Mensal!$A$2:$A$10,$B$3,Resumo_Mensal!$O$2:$O$10)) -> 734
A11: Indicadores calculados a partir de dados fictícios de 01/01 a 17/09/2026. Use o seletor de período para atualizar os KPIs.
A13: Mês | B13: Faturamento | C13: Lucro | D13: Clientes | E13: Combos | F13: Recompra
A14: Jan | B14: =Resumo_Mensal!F2 -> 52689.98 | C14: =Resumo_Mensal!I2 -> 21832.52 | D14: =Resumo_Mensal!B2 -> 1854 | E14: =Resumo_Mensal!L2 -> 509 | F14: =Resumo_Mensal!K2 -> 0.4368932
A15: Fev | B15: =Resumo_Mensal!F3 -> 47546.06 | C15: =Resumo_Mensal!I3 -> 19645.17 | D15: =Resumo_Mensal!B3 -> 1654 | E15: =Resumo_Mensal!L3 -> 410 | F15: =Resumo_Mensal!K3 -> 0.44558646
A16: Mar | B16: =Resumo_Mensal!F4 -> 48871.96 | C16: =Resumo_Mensal!I4 -> 20707 | D16: =Resumo_Mensal!B4 -> 1704 | E16: =Resumo_Mensal!L4 -> 453 | F16: =Resumo_Mensal!K4 -> 0.44600939
A17: Abr | B17: =Resumo_Mensal!F5 -> 45522.27 | C17: =Resumo_Mensal!I5 -> 19233.18 | D17: =Resumo_Mensal!B5 -> 1580 | E17: =Resumo_Mensal!L5 -> 413 | F17: =Resumo_Mensal!K5 -> 0.44113924
A18: Mai | B18: =Resumo_Mensal!F6 -> 47730.74 | C18: =Resumo_Mensal!I6 -> 20357.05 | D18: =Resumo_Mensal!B6 -> 1668 | E18: =Resumo_Mensal!L6 -> 444 | F18: =Resumo_Mensal!K6 -> 0.43405276
A19: Jun | B19: =Resumo_Mensal!F7 -> 49042.79 | C19: =Resumo_Mensal!I7 -> 20727.84 | D19: =Resumo_Mensal!B7 -> 1703 | E19: =Resumo_Mensal!L7 -> 446 | F19: =Resumo_Mensal!K7 -> 0.44509689
A20: Jul | B20: =Resumo_Mensal!F8 -> 52913.6 | C20: =Resumo_Mensal!I8 -> 22244.91 | D20: =Resumo_Mensal!B8 -> 1876 | E20: =Resumo_Mensal!L8 -> 503 | F20: =Resumo_Mensal!K8 -> 0.42963753
A21: Ago | B21: =Resumo_Mensal!F9 -> 50519.7 | C21: =Resumo_Mensal!I9 -> 20977.16 | D21: =Resumo_Mensal!B9 -> 1757 | E21: =Resumo_Mensal!L9 -> 474 | F21: =Resumo_Mensal!K9 -> 0.42401821
A22: Set | B22: =Resumo_Mensal!F10 -> 24223.59 | C22: =Resumo_Mensal!I10 -> 10240.09 | D22: =Resumo_Mensal!B10 -> 836 | E22: =Resumo_Mensal!L10 -> 230 | F22: =Resumo_Mensal!K10 -> 0.42464115
A25: Mês | B25: Clientes | C25: Combos
A26: Jan | B26: =Resumo_Mensal!B2 -> 1854 | C26: =Resumo_Mensal!L2 -> 509
A27: Fev | B27: =Resumo_Mensal!B3 -> 1654 | C27: =Resumo_Mensal!L3 -> 410
A28: Mar | B28: =Resumo_Mensal!B4 -> 1704 | C28: =Resumo_Mensal!L4 -> 453
A29: Abr | B29: =Resumo_Mensal!B5 -> 1580 | C29: =Resumo_Mensal!L5 -> 413
A30: Mai | B30: =Resumo_Mensal!B6 -> 1668 | C30: =Resumo_Mensal!L6 -> 444
A31: Jun | B31: =Resumo_Mensal!B7 -> 1703 | C31: =Resumo_Mensal!L7 -> 446
A32: Jul | B32: =Resumo_Mensal!B8 -> 1876 | C32: =Resumo_Mensal!L8 -> 503
A33: Ago | B33: =Resumo_Mensal!B9 -> 1757 | C33: =Resumo_Mensal!L9 -> 474
A34: Set | B34: =Resumo_Mensal!B10 -> 836 | C34: =Resumo_Mensal!L10 -> 230

Sheet Dados_Diarios
A1: Data | B1: Mês | C1: Dia | D1: Clientes | E1: Novos | F1: Recorrentes | G1: Pedidos | H1: Faturamento | I1: CMV | J1: Custos Operacionais | K1: Combos | L1: X-Tudo | M1: X-Salada | N1: X-Burger | O1: Fritas | P1: Cartões Fidelidade | Q1: Cartões Completos | R1: Cupons Usados | S1: Vendas Promoção
A2: 46023 | B2: Jan | C2: Qui | D2: 49 | E2: 29 | F2: 20 | G2: 47 | H2: 1406.18 | I2: 490.52 | J2: 370.57 | K2: 10 | L2: 12 | M2: 9 | N2: 10 | O2: 16 | P2: 3 | Q2: 0 | R2: 2 | S2: 8
A3: 46024 | B3: Jan | C3: Sex | D3: 69 | E3: 42 | F3: 27 | G3: 68 | H3: 2200.25 | I3: 693.79 | J3: 568.43 | K3: 20 | L3: 17 | M3: 13 | N3: 18 | O3: 22 | P3: 5 | Q3: 1 | R3: 2 | S3: 14
A4: 46025 | B4: Jan | C4: Sáb | D4: 99 | E4: 55 | F4: 44 | G4: 102 | H4: 3036.66 | I4: 1040.37 | J4: 788.82 | K4: 29 | L4: 30 | M4: 22 | N4: 25 | O4: 29 | P4: 8 | Q4: 1 | R4: 4 | S4: 11
A5: 46026 | B5: Jan | C5: Dom | D5: 51 | E5: 32 | F5: 19 | G5: 49 | H5: 1436.39 | I5: 478.66 | J5: 333.55 | K5: 11 | L5: 12 | M5: 12 | N5: 12 | O5: 18 | P5: 4 | Q5: 0 | R5: 3 | S5: 6
A6: 46027 | B6: Jan | C6: Seg | D6: 41 | E6: 23 | F6: 18 | G6: 41 | H6: 1252.84 | I6: 443.25 | J6: 280.31 | K6: 8 | L6: 10 | M6: 8 | N6: 8 | O6: 17 | P6: 5 | Q6: 1 | R6: 2 | S6: 7
A7: 46028 | B7: Jan | C7: Ter | D7: 42 | E7: 21 | F7: 21 | G7: 41 | H7: 1110.66 | I7: 363.55 | J7: 270.65 | K7: 10 | L7: 11 | M7: 10 | N7: 9 | O7: 13 | P7: 5 | Q7: 0 | R7: 2 | S7: 5
A8: 46029 | B8: Jan | C8: Qua | D8: 51 | E8: 26 | F8: 25 | G8: 50 | H8: 1294.06 | I8: 432.32 | J8: 349.1 | K8: 14 | L8: 15 | M8: 12 | N8: 10 | O8: 19 | P8: 5 | Q8: 1 | R8: 3 | S8: 7
A9: 46030 | B9: Jan | C9: Qui | D9: 56 | E9: 35 | F9: 21 | G9: 55 | H9: 1552.23 | I9: 562.98 | J9: 407.54 | K9: 13 | L9: 15 | M9: 11 | N9: 14 | O9: 22 | P9: 5 | Q9: 0 | R9: 3 | S9: 10
A10: 46031 | B10: Jan | C10: Sex | D10: 72 | E10: 37 | F10: 35 | G10: 71 | H10: 1952.74 | I10: 646.76 | J10: 412.36 | K10: 23 | L10: 21 | M10: 17 | N10: 15 | O10: 20 | P10: 9 | Q10: 1 | R10: 5 | S10: 8
A11: 46032 | B11: Jan | C11: Sáb | D11: 80 | E11: 50 | F11: 30 | G11: 80 | H11: 2567.6 | I11: 825.28 | J11: 612.42 | K11: 22 | L11: 20 | M11: 19 | N11: 18 | O11: 25 | P11: 8 | Q11: 1 | R11: 5 | S11: 10
A12: 46033 | B12: Jan | C12: Dom | D12: 74 | E12: 42 | F12: 32 | G12: 73 | H12: 1914.5 | I12: 624.58 | J12: 440.88 | K12: 21 | L12: 18 | M12: 14 | N12: 14 | O12: 27 | P12: 6 | Q12: 0 | R12: 5 | S12: 15
A13: 46034 | B13: Jan | C13: Seg | D13: 36 | E13: 22 | F13: 14 | G13: 36 | H13: 964.28 | I13: 310.13 | J13: 256.62 | K13: 10 | L13: 9 | M13: 8 | N13: 9 | O13: 11 | P13: 2 | Q13: 0 | R13: 2 | S13: 5
... A261: 46282 | B261: Set | C261: Qui | D261: 45 | E261: 26 | F261: 19 | G261: 44 | H261: 1296.95 | I261: 463.53 | J261: 335.12 | K261: 13 | L261: 10 | M261: 10 | N261: 10 | O261: 13 | P261: 6 | Q261: 1 | R261: 3 | S261: 10

Sheet Resumo_Mensal
A1: Mês | B1: Clientes | C1: Novos | D1: Recorrentes | E1: Pedidos | F1: Faturamento | G1: CMV | H1: Custos Op. | I1: Lucro Operacional | J1: Ticket Médio | K1: Taxa Recompra | L1: Combos | M1: Cartões | N1: Completos | O1: Cupons | P1: Vendas Promoção
A2: Jan | B2: =SUMIF(Dados_Diarios!$B$2:$B$261,A2,Dados_Diarios!$D$2:$D$261) -> 1854 | C2: =SUMIF(Dados_Diarios!$B$2:$B$261,A2,Dados_Diarios!$E$2:$E$261) -> 1044 | D2: =SUMIF(Dados_Diarios!$B$2:$B$261,A2,Dados_Diarios!$F$2:$F$261) -> 810 | E2: =SUMIF(Dados_Diarios!$B$2:$B$261,A2,Dados_Diarios!$G$2:$G$261) -> 1823 | F2: =SUMIF(Dados_Diarios!$B$2:$B$261,A2,Dados_Diarios!$H$2:$H$261) -> 52689.98 | G2: =SUMIF(Dados_Diarios!$B$2:$B$261,A2,Dados_Diarios!$I$2:$I$261) -> 18002.2 | H2: =SUMIF(Dados_Diarios!$B$2:$B$261,A2,Dados_Diarios!$J$2:$J$261) -> 12855.26 | I2: =F2-G2-H2 -> 21832.52 | J2: =IFERROR(F2/E2,0) -> 28.902896 | K2: =IFERROR(D2/B2,0) -> 0.4368932 | L2: =SUMIF(Dados_Diarios!$B$2:$B$261,A2,Dados_Diarios!$K$2:$K$261) -> 509 | M2: =SUMIF(Dados_Diarios!$B$2:$B$261,A2,Dados_Diarios!$P$2:$P$261) -> 169 | N2: =SUMIF(Dados_Diarios!$B$2:$B$261,A2,Dados_Diarios!$Q$2:$Q$261) -> 18 | O2: =SUMIF(Dados_Diarios!$B$2:$B$261,A2,Dados_Diarios!$R$2:$R$261) -> 94 | P2: =SUMIF(Dados_Diarios!$B$2:$B$261,A2,Dados_Diarios!$S$2:$S$261) -> 289
A3: Fev | B3: =SUMIF(Dados_Diarios!$B$2:$B$261,A3,Dados_Diarios!$D$2:$D$261) -> 1654 | C3: =SUMIF(Dados_Diarios!$B$2:$B$261,A3,Dados_Diarios!$E$2:$E$261) -> 917 | D3: =SUMIF(Dados_Diarios!$B$2:$B$261,A3,Dados_Diarios!$F$2:$F$261) -> 737 | E3: =SUMIF(Dados_Diarios!$B$2:$B$261,A3,Dados_Diarios!$G$2:$G$261) -> 1622 | F3: =SUMIF(Dados_Diarios!$B$2:$B$261,A3,Dados_Diarios!$H$2:$H$261) -> 47546.06 | G3: =SUMIF(Dados_Diarios!$B$2:$B$261,A3,Dados_Diarios!$I$2:$I$261) -> 16323.34 | H3: =SUMIF(Dados_Diarios!$B$2:$B$261,A3,Dados_Diarios!$J$2:$J$261) -> 11577.55 | I3: =F3-G3-H3 -> 19645.17 | J3: =IFERROR(F3/E3,0) -> 29.313231 | K3: =IFERROR(D3/B3,0) -> 0.44558646 | L3: =SUMIF(Dados_Diarios!$B$2:$B$261,A3,Dados_Diarios!$K$2:$K$261) -> 410 | M3: =SUMIF(Dados_Diarios!$B$2:$B$261,A3,Dados_Diarios!$P$2:$P$261) -> 158 | N3: =SUMIF(Dados_Diarios!$B$2:$B$261,A3,Dados_Diarios!$Q$2:$Q$261) -> 18 | O3: =SUMIF(Dados_Diarios!$B$2:$B$261,A3,Dados_Diarios!$R$2:$R$261) -> 83 | P3: =SUMIF(Dados_Diarios!$B$2:$B$261,A3,Dados_Diarios!$S$2:$S$261) -> 262
A4: Mar | B4: =SUMIF(Dados_Diarios!$B$2:$B$261,A4,Dados_Diarios!$D$2:$D$261) -> 1704 | C4: =SUMIF(Dados_Diarios!$B$2:$B$261,A4,Dados_Diarios!$E$2:$E$261) -> 944 | D4: =SUMIF(Dados_Diarios!$B$2:$B$261,A4,Dados_Diarios!$F$2:$F$261) -> 760 | E4: =SUMIF(Dados_Diarios!$B$2:$B$261,A4,Dados_Diarios!$G$2:$G$261) -> 1678 | F4: =SUMIF(Dados_Diarios!$B$2:$B$261,A4,Dados_Diarios!$H$2:$H$261) -> 48871.96 | G4: =SUMIF(Dados_Diarios!$B$2:$B$261,A4,Dados_Diarios!$I$2:$I$261) -> 16570.84 | H4: =SUMIF(Dados_Diarios!$B$2:$B$261,A4,Dados_Diarios!$J$2:$J$261) -> 11594.12 | I4: =F4-G4-H4 -> 20707 | J4: =IFERROR(F4/E4,0) -> 29.125125 | K4: =IFERROR(D4/B4,0) -> 0.44600939 | L4: =SUMIF(Dados_Diarios!$B$2:$B$261,A4,Dados_Diarios!$K$2:$K$261) -> 453 | M4: =SUMIF(Dados_Diarios!$B$2:$B$261,A4,Dados_Diarios!$P$2:$P$261) -> 171 | N4: =SUMIF(Dados_Diarios!$B$2:$B$261,A4,Dados_Diarios!$Q$2:$Q$261) -> 17 | O4: =SUMIF(Dados_Diarios!$B$2:$B$261,A4,Dados_Diarios!$R$2:$R$261) -> 95 | P4: =SUMIF(Dados_Diarios!$B$2:$B$261,A4,Dados_Diarios!$S$2:$S$261) -> 260
A5: Abr | B5: =SUMIF(Dados_Diarios!$B$2:$B$261,A5,Dados_Diarios!$D$2:$D$261) -> 1580 | C5: =SUMIF(Dados_Diarios!$B$2:$B$261,A5,Dados_Diarios!$E$2:$E$261) -> 883 | D5: =SUMIF(Dados_Diarios!$B$2:$B$261,A5,Dados_Diarios!$F$2:$F$261) -> 697 | E5: =SUMIF(Dados_Diarios!$B$2:$B$261,A5,Dados_Diarios!$G$2:$G$261) -> 1561 | F5: =SUMIF(Dados_Diarios!$B$2:$B$261,A5,Dados_Diarios!$H$2:$H$261) -> 45522.27 | G5: =SUMIF(Dados_Diarios!$B$2:$B$261,A5,Dados_Diarios!$I$2:$I$261) -> 15288.05 | H5: =SUMIF(Dados_Diarios!$B$2:$B$261,A5,Dados_Diarios!$J$2:$J$261) -> 11001.04 | I5: =F5-G5-H5 -> 19233.18 | J5: =IFERROR(F5/E5,0) -> 29.162249 | K5: =IFERROR(D5/B5,0) -> 0.44113924 | L5: =SUMIF(Dados_Diarios!$B$2:$B$261,A5,Dados_Diarios!$K$2:$K$261) -> 413 | M5: =SUMIF(Dados_Diarios!$B$2:$B$261,A5,Dados_Diarios!$P$2:$P$261) -> 149 | N5: =SUMIF(Dados_Diarios!$B$2:$B$261,A5,Dados_Diarios!$Q$2:$Q$261) -> 15 | O5: =SUMIF(Dados_Diarios!$B$2:$B$261,A5,Dados_Diarios!$R$2:$R$261) -> 86 | P5: =SUMIF(Dados_Diarios!$B$2:$B$261,A5,Dados_Diarios!$S$2:$S$261) -> 237
A6: Mai | B6: =SUMIF(Dados_Diarios!$B$2:$B$261,A6,Dados_Diarios!$D$2:$D$261) -> 1668 | C6: =SUMIF(Dados_Diarios!$B$2:$B$261,A6,Dados_Diarios!$E$2:$E$261) -> 944 | D6: =SUMIF(Dados_Diarios!$B$2:$B$261,A6,Dados_Diarios!$F$2:$F$261) -> 724 | E6: =SUMIF(Dados_Diarios!$B$2:$B$261,A6,Dados_Diarios!$G$2:$G$261) -> 1638 | F6: =SUMIF(Dados_Diarios!$B$2:$B$261,A6,Dados_Diarios!$H$2:$H$261) -> 47730.74 | G6: =SUMIF(Dados_Diarios!$B$2:$B$261,A6,Dados_Diarios!$I$2:$I$261) -> 16074.13 | H6: =SUMIF(Dados_Diarios!$B$2:$B$261,A6,Dados_Diarios!$J$2:$J$261) -> 11299.56 | I6: =F6-G6-H6 -> 20357.05 | J6: =IFERROR(F6/E6,0) -> 29.139646 | K6: =IFERROR(D6/B6,0) -> 0.43405276 | L6: =SUMIF(Dados_Diarios!$B$2:$B$261,A6,Dados_Diarios!$K$2:$K$261) -> 444 | M6: =SUMIF(Dados_Diarios!$B$2:$B$261,A6,Dados_Diarios!$P$2:$P$261) -> 158 | N6: =SUMIF(Dados_Diarios!$B$2:$B$261,A6,Dados_Diarios!$Q$2:$Q$261) -> 21 | O6: =SUMIF(Dados_Diarios!$B$2:$B$261,A6,Dados_Diarios!$R$2:$R$261) -> 84 | P6: =SUMIF(Dados_Diarios!$B$2:$B$261,A6,Dados_Diarios!$S$2:$S$261) -> 254
A7: Jun | B7: =SUMIF(Dados_Diarios!$B$2:$B$261,A7,Dados_Diarios!$D$2:$D$261) -> 1703 | C7: =SUMIF(Dados_Diarios!$B$2:$B$261,A7,Dados_Diarios!$E$2:$E$261) -> 945 | D7: =SUMIF(Dados_Diarios!$B$2:$B$261,A7,Dados_Diarios!$F$2:$F$261) -> 758 | E7: =SUMIF(Dados_Diarios!$B$2:$B$261,A7,Dados_Diarios!$G$2:$G$261) -> 1653 | F7: =SUMIF(Dados_Diarios!$B$2:$B$261,A7,Dados_Diarios!$H$2:$H$261) -> 49042.79 | G7: =SUMIF(Dados_Diarios!$B$2:$B$261,A7,Dados_Diarios!$I$2:$I$261) -> 16649.88 | H7: =SUMIF(Dados_Diarios!$B$2:$B$261,A7,Dados_Diarios!$J$2:$J$261) -> 11665.07 | I7: =F7-G7-H7 -> 20727.84 | J7: =IFERROR(F7/E7,0) -> 29.668959 | K7: =IFERROR(D7/B7,0) -> 0.44509689 | L7: =SUMIF(Dados_Diarios!$B$2:$B$261,A7,Dados_Diarios!$K$2:$K$261) -> 446 | M7: =SUMIF(Dados_Diarios!$B$2:$B$261,A7,Dados_Diarios!$P$2:$P$261) -> 161 | N7: =SUMIF(Dados_Diarios!$B$2:$B$261,A7,Dados_Diarios!$Q$2:$Q$261) -> 20 | O7: =SUMIF(Dados_Diarios!$B$2:$B$261,A7,Dados_Diarios!$R$2:$R$261) -> 77 | P7: =SUMIF(Dados_Diarios!$B$2:$B$261,A7,Dados_Diarios!$S$2:$S$261) -> 267
A8: Jul | B8: =SUMIF(Dados_Diarios!$B$2:$B$261,A8,Dados_Diarios!$D$2:$D$261) -> 1876 | C8: =SUMIF(Dados_Diarios!$B$2:$B$261,A8,Dados_Diarios!$E$2:$E$261) -> 1070 | D8: =SUMIF(Dados_Diarios!$B$2:$B$261,A8,Dados_Diarios!$F$2:$F$261) -> 806 | E8: =SUMIF(Dados_Diarios!$B$2:$B$261,A8,Dados_Diarios!$G$2:$G$261) -> 1823 | F8: =SUMIF(Dados_Diarios!$B$2:$B$261,A8,Dados_Diarios!$H$2:$H$261) -> 52913.6 | G8: =SUMIF(Dados_Diarios!$B$2:$B$261,A8,Dados_Diarios!$I$2:$I$261) -> 17987.96 | H8: =SUMIF(Dados_Diarios!$B$2:$B$261,A8,Dados_Diarios!$J$2:$J$261) -> 12680.73 | I8: =F8-G8-H8 -> 22244.91 | J8: =IFERROR(F8/E8,0) -> 29.025562 | K8: =IFERROR(D8/B8,0) -> 0.42963753 | L8: =SUMIF(Dados_Diarios!$B$2:$B$261,A8,Dados_Diarios!$K$2:$K$261) -> 503 | M8: =SUMIF(Dados_Diarios!$B$2:$B$261,A8,Dados_Diarios!$P$2:$P$261) -> 198 | N8: =SUMIF(Dados_Diarios!$B$2:$B$261,A8,Dados_Diarios!$Q$2:$Q$261) -> 21 | O8: =SUMIF(Dados_Diarios!$B$2:$B$261,A8,Dados_Diarios!$R$2:$R$261) -> 89 | P8: =SUMIF(Dados_Diarios!$B$2:$B$261,A8,Dados_Diarios!$S$2:$S$261) -> 290
A9: Ago | B9: =SUMIF(Dados_Diarios!$B$2:$B$261,A9,Dados_Diarios!$D$2:$D$261) -> 1757 | C9: =SUMIF(Dados_Diarios!$B$2:$B$261,A9,Dados_Diarios!$E$2:$E$261) -> 1012 | D9: =SUMIF(Dados_Diarios!$B$2:$B$261,A9,Dados_Diarios!$F$2:$F$261) -> 745 | E9: =SUMIF(Dados_Diarios!$B$2:$B$261,A9,Dados_Diarios!$G$2:$G$261) -> 1711 | F9: =SUMIF(Dados_Diarios!$B$2:$B$261,A9,Dados_Diarios!$H$2:$H$261) -> 50519.7 | G9: =SUMIF(Dados_Diarios!$B$2:$B$261,A9,Dados_Diarios!$I$2:$I$261) -> 17327.09 | H9: =SUMIF(Dados_Diarios!$B$2:$B$261,A9,Dados_Diarios!$J$2:$J$261) -> 12215.45 | I9: =F9-G9-H9 -> 20977.16 | J9: =IFERROR(F9/E9,0) -> 29.526417 | K9: =IFERROR(D9/B9,0) -> 0.42401821 | L9: =SUMIF(Dados_Diarios!$B$2:$B$261,A9,Dados_Diarios!$K$2:$K$261) -> 474 | M9: =SUMIF(Dados_Diarios!$B$2:$B$261,A9,Dados_Diarios!$P$2:$P$261) -> 176 | N9: =SUMIF(Dados_Diarios!$B$2:$B$261,A9,Dados_Diarios!$Q$2:$Q$261) -> 22 | O9: =SUMIF(Dados_Diarios!$B$2:$B$261,A9,Dados_Diarios!$R$2:$R$261) -> 81 | P9: =SUMIF(Dados_Diarios!$B$2:$B$261,A9,Dados_Diarios!$S$2:$S$261) -> 293
A10: Set | B10: =SUMIF(Dados_Diarios!$B$2:$B$261,A10,Dados_Diarios!$D$2:$D$261) -> 836 | C10: =SUMIF(Dados_Diarios!$B$2:$B$261,A10,Dados_Diarios!$E$2:$E$261) -> 481 | D10: =SUMIF(Dados_Diarios!$B$2:$B$261,A10,Dados_Diarios!$F$2:$F$261) -> 355 | E10: =SUMIF(Dados_Diarios!$B$2:$B$261,A10,Dados_Diarios!$G$2:$G$261) -> 824 | F10: =SUMIF(Dados_Diarios!$B$2:$B$261,A10,Dados_Diarios!$H$2:$H$261) -> 24223.59 | G10: =SUMIF(Dados_Diarios!$B$2:$B$261,A10,Dados_Diarios!$I$2:$I$261) -> 8258.69 | H10: =SUMIF(Dados_Diarios!$B$2:$B$261,A10,Dados_Diarios!$J$2:$J$261) -> 5724.81 | I10: =F10-G10-H10 -> 10240.09 | J10: =IFERROR(F10/E10,0) -> 29.397561 | K10: =IFERROR(D10/B10,0) -> 0.42464115 | L10: =SUMIF(Dados_Diarios!$B$2:$B$261,A10,Dados_Diarios!$K$2:$K$261) -> 230 | M10: =SUMIF(Dados_Diarios!$B$2:$B$261,A10,Dados_Diarios!$P$2:$P$261) -> 78 | N10: =SUMIF(Dados_Diarios!$B$2:$B$261,A10,Dados_Diarios!$Q$2:$Q$261) -> 8 | O10: =SUMIF(Dados_Diarios!$B$2:$B$261,A10,Dados_Diarios!$R$2:$R$261) -> 45 | P10: =SUMIF(Dados_Diarios!$B$2:$B$261,A10,Dados_Diarios!$S$2:$S$261) -> 138

Sheet Promocoes
A1: Ação | B1: Canal | C1: Objetivo | D1: Custo estimado | E1: Vendas atribuídas | F1: Receita atribuída | G1: ROI
A2: Lousa Oferta do Dia | B2: Físico | C2: Conversão | D2: 120 | E2: 380 | F2: 9800 | G2: =IFERROR((F2-D2)/D2,0) -> 80.666667
A3: Cartão Fidelidade | B3: Físico | C3: Recompra | D3: 180 | E3: 245 | F3: 7100 | G3: =IFERROR((F3-D3)/D3,0) -> 38.444444
A4: Cupom de Retorno | B4: Físico | C4: Retorno | D4: 140 | E4: 162 | F4: 4650 | G4: =IFERROR((F4-D4)/D4,0) -> 32.214286
A5: Traga a Galera | B5: Físico | C5: Ticket médio | D5: 250 | E5: 118 | F5: 5100 | G5: =IFERROR((F5-D5)/D5,0) -> 19.4
A6: Display de Combo | B6: Balcão | C6: Upsell | D6: 90 | E6: 420 | F6: 8900 | G6: =IFERROR((F6-D6)/D6,0) -> 97.888889
A7: Posts/Stories locais | B7: Digital | C7: Descoberta | D7: 350 | E7: 205 | F7: 5700 | G7: =IFERROR((F7-D7)/D7,0) -> 15.285714

Sheet Produtos
A1: Produto | B1: Unidades | C1: Preço médio | D1: Receita | E1: Participação | F1: Margem estimada | G1: Observação
A2: X-Tudo | B2: =SUM(Dados_Diarios!$L$2:$L$261) -> 3803 | C2: 30 | D2: =B2*C2 -> 114090 | E2: =IFERROR(D2/SUM($D$2:$D$6),0) -> 0.24202992 | F2: 0.6 | G2: Maior apelo visual; forte em combos
A3: X-Salada | B3: =SUM(Dados_Diarios!$M$2:$M$261) -> 3100 | C3: 25 | D3: =B3*C3 -> 77500 | E3: =IFERROR(D3/SUM($D$2:$D$6),0) -> 0.16440809 | F3: 0.62 | G3: Clássico e recorrente
A4: X-Burger | B4: =SUM(Dados_Diarios!$N$2:$N$261) -> 3330 | C4: 22 | D4: =B4*C4 -> 73260 | E4: =IFERROR(D4/SUM($D$2:$D$6),0) -> 0.15541337 | F4: 0.64 | G4: Entrada de preço
A5: Fritas | B5: =SUM(Dados_Diarios!$O$2:$O$261) -> 4970 | C5: 15 | D5: =B5*C5 -> 74550 | E5: =IFERROR(D5/SUM($D$2:$D$6),0) -> 0.15814997 | F5: 0.68 | G5: Complemento e upsell
A6: Combos | B6: =SUM(Dados_Diarios!$K$2:$K$261) -> 3882 | C6: 34 | D6: =B6*C6 -> 131988 | E6: =IFERROR(D6/SUM($D$2:$D$6),0) -> 0.27999864 | F6: 0.58 | G6: Eleva ticket médio

Sheet Parametros
A1: Parâmetro | B1: Valor | D1: Meses
A2: CMV alvo | B2: 0.34 | D2: Todos
A3: Custos operacionais alvo | B3: 0.24 | D3: Jan
A4: Ticket médio alvo | B4: 28 | D4: Fev
A5: Taxa recompra alvo | B5: 0.42 | D5: Mar
A6: Conversão fidelidade alvo | B6: 0.12 | D6: Abr
A7: Uso cupom alvo | B7: 0.08 | D7: Mai
A8: Meta faturamento mensal | B8: 42000 | D8: Jun
A9: Meta clientes/mês | B9: 1350 | D9: Jul
A10: Meta combos/mês | B10: 350 | D10: Ago
A11: Meta cartões fidelidade/mês | B11: 120 | D11: Set
A12: Meta promoções presenciais/mês | B12: 250
